img_processing_project_dio/__init__.py
img_processing_project_dio/processing/__init__.py
img_processing_project_dio/processing/combination.py
img_processing_project_dio/processing/transformation.py
img_processing_project_dio/utils/__init__.py
img_processing_project_dio/utils/io.py
img_processing_project_dio/utils/plot.py
img_processing_project_dio-0.0.6.dist-info/METADATA
img_processing_project_dio-0.0.6.dist-info/WHEEL
img_processing_project_dio-0.0.6.dist-info/top_level.txt
img_processing_project_dio-0.0.6.dist-info/RECORD
