Metadata-Version: 2.1
Name: img-processing-project-dio
Version: 0.0.6
Summary: This project is part of a bootcamp
Home-page: https://github.com/BetaTH/image_processing_th.git
Author: Thielson Alemendra
Author-email: thielson12@gmail.com
License: UNKNOWN
Platform: UNKNOWN
Requires-Python: >=3.8
Requires-Dist: matplotlib
Requires-Dist: scikit-image
Requires-Dist: numpy
